setup.py
spy_probability/Binomialdistribution.py
spy_probability/Gaussiandistribution.py
spy_probability/Generaldistribution.py
spy_probability/__init__.py
spy_probability.egg-info/PKG-INFO
spy_probability.egg-info/SOURCES.txt
spy_probability.egg-info/dependency_links.txt
spy_probability.egg-info/not-zip-safe
spy_probability.egg-info/top_level.txt