Metadata-Version: 1.0
Name: spy-probability
Version: 0.2
Summary: Gaussian and Binomial distributions
Home-page: UNKNOWN
Author: Aguwa Obinna
Author-email: macmartins081@gmail.com
License: UNKNOWN
Platform: UNKNOWN
